Metadata-Version: 2.1
Name: wizpy
Version: 0.1.3
Summary: A example Python package
Home-page: https://github.com/Pegacraft/wizPy
Author: Pegacraffft
Author-email: karl.w.schramm@gmail.com
License: Open source
Platform: UNKNOWN
Classifier: Programming Language :: Python :: 3.9
